aquisitionpackagetestor98/__init__.py
aquisitionpackagetestor98/aggregate.py
aquisitionpackagetestor98/collect.py
aquisitionpackagetestor98/driver.py
aquisitionpackagetestor98/init_dicts.py
aquisitionpackagetestor98/parser.py
aquisitionpackagetestor98/save.py
aquisitionpackagetestor98/transfer.py
aquisitionpackagetestor98/utils.py
aquisitionpackagetestor98-0.0.4.dist-info/METADATA
aquisitionpackagetestor98-0.0.4.dist-info/WHEEL
aquisitionpackagetestor98-0.0.4.dist-info/licenses/LICENSE.txt
aquisitionpackagetestor98-0.0.4.dist-info/RECORD
