Metadata-Version: 2.1
Name: aquisitionpackagetestor98
Version: 0.0.4
Summary: Data aquisition package.
Project-URL: Homepage, https://github.com/OR98/or98aquisitionpackage
Project-URL: Bug Tracker, https://github.com/OR98/or98aquisitionpackage/issues
Author-email: OR98 <r.oumhmiz@gmail.com>
License-File: LICENSE.txt
Classifier: License :: OSI Approved :: MIT License
Classifier: Operating System :: OS Independent
Classifier: Programming Language :: Python :: 3
Requires-Python: >=3.7
